<AML>
 <Item type="Permission" id="CFB8203B9A2B46DC9DE9E38AACDD683B" action="add">
  <is_private>0</is_private>
  <name>SRE_releasedPart</name>
  <Relationships>
   <Item type="Access" id="126702CA604D40F482182A4FB9CF3B0E" action="add">
    <can_change_access>0</can_change_access>
    <can_delete>0</can_delete>
    <can_discover>1</can_discover>
    <can_get>1</can_get>
    <can_update>0</can_update>
    <related_id keyed_name="Reader" type="Identity">0F12B7716FE44CDF8192509B8C67A41F</related_id>
    <show_permissions_warning>0</show_permissions_warning>
    <sort_order>512</sort_order>
    <source_id keyed_name="SRE_releasedPart" type="Permission">CFB8203B9A2B46DC9DE9E38AACDD683B</source_id>
   </Item>
   <Item type="Access" id="350D289649924E2AAB10702B8532EE6F" action="add">
    <can_change_access>0</can_change_access>
    <can_delete>0</can_delete>
    <can_discover>1</can_discover>
    <can_get>1</can_get>
    <can_update>1</can_update>
    <related_id keyed_name="Editor" type="Identity">8F78DAAD4DE346AC86878E16720A63A0</related_id>
    <show_permissions_warning>1</show_permissions_warning>
    <sort_order>384</sort_order>
    <source_id keyed_name="SRE_releasedPart" type="Permission">CFB8203B9A2B46DC9DE9E38AACDD683B</source_id>
   </Item>
   <Item type="Access" id="86E53EC2D89545249995EC1E39BC2D47" action="add">
    <can_change_access>1</can_change_access>
    <can_delete>1</can_delete>
    <can_discover>1</can_discover>
    <can_get>1</can_get>
    <can_update>1</can_update>
    <related_id keyed_name="Administrators" type="Identity">2618D6F5A90949BAA7E920D1B04C7EE1</related_id>
    <show_permissions_warning>1</show_permissions_warning>
    <sort_order>768</sort_order>
    <source_id keyed_name="SRE_releasedPart" type="Permission">CFB8203B9A2B46DC9DE9E38AACDD683B</source_id>
   </Item>
   <Item type="Access" id="C643ABCF736F4674B2FB45894C06080D" action="add">
    <can_change_access>0</can_change_access>
    <can_delete>0</can_delete>
    <can_discover>1</can_discover>
    <can_get>1</can_get>
    <can_update>1</can_update>
    <related_id keyed_name="SE5000 All Users" type="Identity">10FAC37B5B9541B88119DB67CEAFB1E7</related_id>
    <show_permissions_warning>0</show_permissions_warning>
    <sort_order>896</sort_order>
    <source_id keyed_name="SRE_releasedPart" type="Permission">CFB8203B9A2B46DC9DE9E38AACDD683B</source_id>
   </Item>
   <Item type="Access" id="F92ED883C30F4ADC80D80E20847D3779" action="add">
    <can_change_access>1</can_change_access>
    <can_delete>1</can_delete>
    <can_discover>1</can_discover>
    <can_get>1</can_get>
    <can_update>1</can_update>
    <related_id keyed_name="SRE_CoreUserGroup" type="Identity">93FA7BC57D0844329494BA5F70976DA4</related_id>
    <show_permissions_warning>1</show_permissions_warning>
    <sort_order>256</sort_order>
    <source_id keyed_name="SRE_releasedPart" type="Permission">CFB8203B9A2B46DC9DE9E38AACDD683B</source_id>
   </Item>
  </Relationships>
 </Item>
</AML>